color_spray/__init__.py
color_spray/__version__.py
color_spray/color_spray.py
color_spray/entry_points.py
color_spray-0.1.0.dist-info/METADATA
color_spray-0.1.0.dist-info/WHEEL
color_spray-0.1.0.dist-info/entry_points.txt
color_spray-0.1.0.dist-info/top_level.txt
color_spray-0.1.0.dist-info/RECORD
